slack_easy/__init__.py
slack_easy/blocks/__init__.py
slack_easy/blocks/actions.py
slack_easy/blocks/context.py
slack_easy/blocks/divider.py
slack_easy/blocks/header.py
slack_easy/blocks/image.py
slack_easy/blocks/input.py
slack_easy/blocks/rich_text.py
slack_easy/blocks/section.py
slack_easy/blocks/table.py
slack_easy/bot/__init__.py
slack_easy/config/__init__.py
slack_easy/file_management/__init__.py
slack_easy/interface/__init__.py
slack_easy/messages/__init__.py
slack_easy/messages/actions/__init__.py
slack_easy/messages/actions/datepickers.py
slack_easy/messages/composite/__init__.py
slack_easy/messages/composite/button.py
slack_easy/messages/composite/checkboxes.py
slack_easy/messages/composite/dataframe.py
slack_easy/messages/composite/radio_buttons.py
slack_easy/messages/composite/time_picker.py
slack_easy/messages/context/__init__.py
slack_easy/messages/context/context.py
slack_easy/messages/header/__init__.py
slack_easy/messages/header/header.py
slack_easy/messages/image/__init__.py
slack_easy/messages/image/image_msg.py
slack_easy/messages/input/__init__.py
slack_easy/messages/rich_text/__init__.py
slack_easy/messages/rich_text/list.py
slack_easy/messages/rich_text/preformatted.py
slack_easy/messages/rich_text/quote.py
slack_easy/messages/rich_text/strike.py
slack_easy/messages/section/__init__.py
slack_easy/messages/section/date_picker.py
slack_easy/messages/section/mrkdwn.py
slack_easy/messages/section/multi_static_select_msg.py
slack_easy/messages/section/overflow.py
slack_easy/messages/section/plain_text.py
slack_easy/messages/section/static_select.py
slack_easy/messages/section/text_fields.py
slack_easy/messages/section/users_select.py
slack_easy/messages/table/__init__.py
slack_easy/messages/table/simple_table.py
slack_easy/utils/__init__.py
slack_easy-0.1.2.dist-info/METADATA
slack_easy-0.1.2.dist-info/WHEEL
slack_easy-0.1.2.dist-info/top_level.txt
slack_easy-0.1.2.dist-info/RECORD
