Metadata-Version: 2.4
Name: slack-easy
Version: 0.1.2
Summary: A flexible and easy-to-use library for creating and sending messages to Slack
Author-email: cw <cw.devworks@gmail.com>
License: Apache-2.0
Classifier: Development Status :: 3 - Alpha
Classifier: Intended Audience :: Developers
Classifier: Programming Language :: Python :: 3
Classifier: Programming Language :: Python :: 3.8
Classifier: Programming Language :: Python :: 3.9
Classifier: Programming Language :: Python :: 3.10
Classifier: Programming Language :: Python :: 3.11
Classifier: Programming Language :: Python :: 3.12
Classifier: Programming Language :: Python :: 3.13
Classifier: Topic :: Software Development :: Libraries :: Python Modules
Classifier: Topic :: Communications
Classifier: Operating System :: OS Independent
Requires-Python: >=3.8
Requires-Dist: python-dotenv
Requires-Dist: slack-sdk
Requires-Dist: tenacity
Requires-Dist: pandas
Requires-Dist: tabulate
